internetarchivesync/__init__.py
internetarchivesync/archive_download.py
internetarchivesync/archive_sync.py
internetarchivesync/download.py
internetarchivesync/io.py
internetarchivesync/logging_config.ini
internetarchivesync/observer.py
internetarchivesync/sync.py
internetarchivesync-1.0.2.dist-info/METADATA
internetarchivesync-1.0.2.dist-info/WHEEL
internetarchivesync-1.0.2.dist-info/entry_points.txt
internetarchivesync-1.0.2.dist-info/RECORD
