Metadata-Version: 2.1
Name: internetarchivesync
Version: 1.0.2
Summary: A python tool to donwload an internet archive.
Author: Mathieu
Author-email: git@bigbisous.org
Requires-Python: >=3.9,<4.0
Classifier: Programming Language :: Python :: 3
Classifier: Programming Language :: Python :: 3.9
Classifier: Programming Language :: Python :: 3.10
Classifier: Programming Language :: Python :: 3.11
Requires-Dist: defusedxml (>=0.7.1,<0.8.0)
Requires-Dist: pytest (>=7.3.1,<8.0.0)
Requires-Dist: requests (>=2.26.0,<3.0.0)
Requires-Dist: rich (>=13.3.5,<14.0.0)
